odoo/addons/base_ir_actions_report_sequence/README.rst
odoo/addons/base_ir_actions_report_sequence/__init__.py
odoo/addons/base_ir_actions_report_sequence/__manifest__.py
odoo/addons/base_ir_actions_report_sequence/i18n/base_ir_actions_report_sequence.pot
odoo/addons/base_ir_actions_report_sequence/models/__init__.py
odoo/addons/base_ir_actions_report_sequence/models/ir_actions.py
odoo/addons/base_ir_actions_report_sequence/static/description/icon.png
odoo/addons/base_ir_actions_report_sequence/static/description/index.html
odoo/addons/base_ir_actions_report_sequence/views/ir_actions_report_views.xml
odoo13_addon_base_ir_actions_report_sequence-13.0.1.0.1.dev1.dist-info/METADATA
odoo13_addon_base_ir_actions_report_sequence-13.0.1.0.1.dev1.dist-info/WHEEL
odoo13_addon_base_ir_actions_report_sequence-13.0.1.0.1.dev1.dist-info/top_level.txt
odoo13_addon_base_ir_actions_report_sequence-13.0.1.0.1.dev1.dist-info/RECORD
